gradio_promptweighting/__init__.py
gradio_promptweighting/promptweighting.py
gradio_promptweighting/promptweighting.pyi
gradio_promptweighting/templates/component/index.js
gradio_promptweighting/templates/component/style.css
gradio_promptweighting/templates/example/index.js
gradio_promptweighting/templates/example/style.css
gradio_promptweighting-0.0.2.dist-info/METADATA
gradio_promptweighting-0.0.2.dist-info/WHEEL
gradio_promptweighting-0.0.2.dist-info/RECORD
